bali/__init__.py
bali/_utils.py
bali/application.py
bali/cache.py
bali/cache_memoize.py
bali/cli.py
bali/core.py
bali/decorators.py
bali/environments.py
bali/exceptions.py
bali/interceptors.py
bali/middlewares.py
bali/mixins.py
bali/paginate.py
bali/permissions.py
bali/routing.py
bali/servicer.py
bali/tasks.py
bali/tests.py
bali/typing.py
bali/aio/__init__.py
bali/aio/interceptors.py
bali/aio/sessions.py
bali/db/__init__.py
bali/db/comparators.py
bali/db/connection.py
bali/db/declarative.py
bali/db/managers.py
bali/db/models.py
bali/db/operators.py
bali/db/session_control.py
bali/db/transaction.py
bali/declarative/__init__.py
bali/events/__init__.py
bali/events/dispatch.py
bali/events/event.py
bali/events/handler.py
bali/resources/__init__.py
bali/resources/generic_routes.py
bali/resources/grpc_actions.py
bali/resources/model_resource.py
bali/resources/resource.py
bali/schemas/__init__.py
bali/schemas/generic.py
bali/utils/__init__.py
bali/utils/dateparse.py
bali/utils/timezone.py
bali_core-3.5.1.dist-info/LICENSE
bali_core-3.5.1.dist-info/METADATA
bali_core-3.5.1.dist-info/WHEEL
bali_core-3.5.1.dist-info/top_level.txt
bali_core-3.5.1.dist-info/RECORD
