Metadata-Version: 2.1
Name: bali-core
Version: 3.5.1
Summary: Simplify FastAPI integrate gRPC services development
Home-page: https://github.com/bali-framework/bali
Author: Josh.Yu
Author-email: josh.yu_8@live.com
License: MIT
Platform: UNKNOWN
Classifier: Intended Audience :: Developers
Classifier: Development Status :: 5 - Production/Stable
Classifier: Topic :: Internet
Classifier: Topic :: Software Development :: Libraries :: Application Frameworks
Classifier: Topic :: Software Development :: Libraries :: Python Modules
Classifier: Topic :: Software Development :: Libraries
Classifier: Topic :: Software Development
Classifier: Topic :: Internet :: WWW/HTTP :: HTTP Servers
Classifier: Topic :: Internet :: WWW/HTTP
Classifier: Environment :: Web Environment
Classifier: License :: OSI Approved :: MIT License
Classifier: Programming Language :: Python :: 3 :: Only
Classifier: Programming Language :: Python :: 3.7
Classifier: Programming Language :: Python :: 3.8
Classifier: Programming Language :: Python :: 3.9
Classifier: Programming Language :: Python :: 3.10
Requires-Dist: greenlet <=2.0.1,>1.0
Requires-Dist: aiomysql
Requires-Dist: aiosqlite
Requires-Dist: dateparser >=1.1.0
Requires-Dist: fastapi[all] <=0.92,>=0.69.0
Requires-Dist: fastapi-migrate ==0.1.1
Requires-Dist: fastapi-pagination <=0.10,>=0.9.0
Requires-Dist: grpcio <=1.50.0,>=1.32.0
Requires-Dist: grpcio-tools <=1.50.0,>=1.32.0
Requires-Dist: grpc-interceptor ==0.15.0
Requires-Dist: importlib-metadata <5.0.0
Requires-Dist: kombu <6.0,>=5.2.4
Requires-Dist: MarkupSafe ==2.0.1
Requires-Dist: PyMySQL <=1.0.2,>=0.9
Requires-Dist: passlib[bcrypt] ==1.7.2
Requires-Dist: pillow <8.4,>=7.2.0
Requires-Dist: pydantic-sqlalchemy <1,>=0.0.7
Requires-Dist: pyhumps
Requires-Dist: pytz ==2021.1
Requires-Dist: redis <4.3,>=3.5.3
Requires-Dist: regex ==2022.1.18
Requires-Dist: sqla-wrapper <5.6,>=5.0.0
Requires-Dist: typer >=0.4
